django_auto_healthchecks/__init__.py
django_auto_healthchecks/apps.py
django_auto_healthchecks/healthchecks.py
django_auto_healthchecks-0.1.5.dist-info/DESCRIPTION.rst
django_auto_healthchecks-0.1.5.dist-info/METADATA
django_auto_healthchecks-0.1.5.dist-info/RECORD
django_auto_healthchecks-0.1.5.dist-info/WHEEL
django_auto_healthchecks-0.1.5.dist-info/metadata.json
django_auto_healthchecks-0.1.5.dist-info/top_level.txt
