Metadata-Version: 2.0
Name: django-auto-healthchecks
Version: 0.1.5
Summary: Create application health checks directly from your django urls.py
Home-page: https://github.com/cronitorio/django_auto_healthchecks
Author: Cronitor.io
Author-email: support@cronitor.io
License: MIT license
Keywords: django_auto_healthchecks
Platform: UNKNOWN
Classifier: Development Status :: 2 - Pre-Alpha
Classifier: Intended Audience :: Developers
Classifier: License :: OSI Approved :: MIT License
Classifier: Natural Language :: English
Classifier: Programming Language :: Python :: 2
Classifier: Programming Language :: Python :: 2.7
Classifier: Programming Language :: Python :: 3
Classifier: Programming Language :: Python :: 3.4
Classifier: Programming Language :: Python :: 3.5
Requires-Dist: future (==0.16.0)
Requires-Dist: requests (==2.13.0)
